<?xml version="1.0" encoding="UTF-8"?>
<appendix xmlns="http://docbook.org/ns/docbook" xmlns:xi="http://www.w3.org/2001/XInclude" xmlns:xlink="http://www.w3.org/1999/xlink" xml:base="deployment_docupdates.xml" version="5.0" xml:id="ap-deploy-docupdate">
 <title>Aktualisierungen der Dokumentation</title>
 <info>
  <dm:docmanager xmlns:dm="urn:x-suse:ns:docmanager">
   <dm:editurl>https://github.com/SUSE/doc-ses/edit/maintenance/ses6/xml/</dm:editurl>
   <dm:maintainer>tbazant@suse.com</dm:maintainer>
   <dm:status>Bearbeiten</dm:status>
   <dm:deadline/>
   <dm:priority/>
   <dm:translation>Ja</dm:translation>
   <dm:languages/>
   <dm:release>SES 6</dm:release>
  </dm:docmanager>
 </info>
 <para>
  In diesem Kapitel finden Sie eine Liste der geänderten Inhalte seit der Freigabe des aktuellen Wartungs-Updates von SUSE Enterprise Storage 5. Sie finden die Änderungen, die sich auf die Cluster-Bereitstellung beziehen und auf frühere Versionen zutreffen unter <link xlink:href="https://www.suse.com/documentation/suse-enterprise-storage-5/book_storage_deployment/data/ap_deploy_docupdate.html"/>.
 </para>
 <para>
  Die Dokumentation wurde an folgenden Terminen aktualisiert:
 </para>

 <itemizedlist mark="bullet" spacing="normal">
  <listitem>
   <para>
    <xref linkend="sec-depl-docupdates-6mu" xrefstyle="SectTitleOnPage"/>
   </para>
  </listitem>
  <listitem>
   <para>
    <xref linkend="sec-depl-docupdates-6" xrefstyle="SectTitleOnPage"/>
   </para>
  </listitem>
 </itemizedlist>

 <sect1 xml:id="sec-depl-docupdates-6mu">
  <title>Wartungs-Update der Dokumentation zu SUSE Enterprise Storage 6</title>

  <itemizedlist mark="bullet" spacing="normal">
   <title>Allgemeine Aktualisierungen</title>
   <listitem>
    <para>
     Die Ausführung von <command>rpmconfigcheck</command> zur Vermeidung des Verlusts lokaler Änderungen wurde in <xref linkend="upgrade-one-node"/> vorgeschlagen (<link xlink:href="https://jira.suse.com/browse/SES-348"/>).
    </para>
   </listitem>
   <listitem>
    <para>
     <xref linkend="lvmcache"/> wurde hinzugefügt (<link xlink:href="https://jira.suse.com/browse/SES-269"/>).
    </para>
   </listitem>
   <listitem>
    <para>
     <xref linkend="cha-container-kubernetes"/> wurde hinzugefügt (<link xlink:href="https://jira.suse.com/browse/SES-720"/>).
    </para>
   </listitem>
  </itemizedlist>

  <itemizedlist mark="bullet" spacing="normal">
   <title>Fehlerbehebungen</title>
   <listitem>
    <para>
     Tipps zur Überwachung des Status der Cluster Nodes beim Upgrade wurden in <xref linkend="upgrade-adm"/> eingefügt (<link xlink:href="https://bugzilla.suse.com/show_bug.cgi?id=1154568"/>).
    </para>
   </listitem>
   <listitem>
    <para>
     <xref linkend="upgrade-one-node-auto"/> (<link xlink:href="https://bugzilla.suse.com/show_bug.cgi?id=1154438"/>) hinzugefügt.
    </para>
   </listitem>
   <listitem>
    <para>
     Das Kapitel zum Upgrade wurde zeitlich geordnet, <xref linkend="cha-ceph-upgrade"/> (<link xlink:href="https://bugzilla.suse.com/show_bug.cgi?id=1144709"/>).
    </para>
   </listitem>
   <listitem>
    <para>
     Ein Änderungsprotokolleintrag für Ceph 14.2.4 wurde hinzugefügt (<link xlink:href="https://bugzilla.suse.com/show_bug.cgi?id=1151881"/>).
    </para>
   </listitem>
   <listitem>
    <para>
     Der Pool-Name in den Beispielen in <xref linkend="cha-as-ganesha"/> wurde vereinheitlicht und lautet nunmehr „cephfs_metadata“ (<link xlink:href="https://bugzilla.suse.com/show_bug.cgi?id=1148548"/>).
    </para>
   </listitem>
   <listitem>
    <para>
     <xref linkend="ds-drive-groups-specs"/> wurde mit realistischeren Werten aktualisiert (<link xlink:href="https://bugzilla.suse.com/show_bug.cgi?id=1148216"/>).
    </para>
   </listitem>
   <listitem>
    <para>
     Zwei neue Repositorys für „Module-Desktop“ wurden in <xref linkend="upgrade-one-node-manual"/> eingefügt, da unsere Kunden hauptsächlich mit der GUI arbeiten (<link xlink:href="https://bugzilla.suse.com/show_bug.cgi?id=1144897"/>).
    </para>
   </listitem>
   <listitem>
    <para>
     <package>deepsea-cli</package> ist kein untergeordnetes Element von
     <package>deepsea</package> in <xref linkend="deepsea-cli"/> (<link xlink:href="https://bugzilla.suse.com/show_bug.cgi?id=1143602"/>).
    </para>
   </listitem>
   <listitem>
    <para>
     Ein Hinweis zur Migration von <systemitem class="daemon">ntpd</systemitem> zu <systemitem class="daemon">chronyd</systemitem> wurde in <xref linkend="upgrade-consider-points"/> eingefügt (<link xlink:href="https://bugzilla.suse.com/show_bug.cgi?id=1135185"/>).
    </para>
   </listitem>
   <listitem>
    <para>
     <xref linkend="deactivate-tuned-profiles"/> (<link xlink:href="https://bugzilla.suse.com/show_bug.cgi?id=1130430"/>) hinzugefügt.
    </para>
   </listitem>
   <listitem>
    <para>
     Überlegungen zur Migration des ganzen OSD Nodes wurden in <xref linkend="upgrade-osd-deployment"/> eingefügt (<link xlink:href="https://bugzilla.suse.com/show_bug.cgi?id=1138691"/>).
    </para>
   </listitem>
   <listitem>
    <para>
     Ein Punkt zur Migration von MDS-Namen wurde in <xref linkend="upgrade-consider-points"/> eingefügt (<link xlink:href="https://bugzilla.suse.com/show_bug.cgi?id=1138804"/>).
    </para>
   </listitem>
  </itemizedlist>
 </sect1>
 <sect1 xml:id="sec-depl-docupdates-6">
  <title>Juni 2019 (Freigabe von SUSE Enterprise Storage 6)</title>

  <itemizedlist mark="bullet" spacing="normal">
   <title>Allgemeine Aktualisierungen</title>
   <listitem>
    <para>
     <xref linkend="ds-drive-groups"/> wurde hinzugefügt (jsc#SES-548).
    </para>
   </listitem>
   <listitem>
    <para>
     <xref linkend="cha-ceph-upgrade"/> wurde umgeschrieben (jsc#SES-88).
    </para>
   </listitem>
   <listitem>
    <para>
     <xref linkend="ds-modify-ipv6"/> wurde hinzugefügt (jsc#SES-409).
    </para>
   </listitem>
   <listitem>
    <para>
     Die Blockspeicherung wurde als standardmäßiges Speicher-Back-End festgelegt (Fate-Nr. 325658).
    </para>
   </listitem>
   <listitem>
    <para>
     Alle Verweise auf externe online-Dokumentation wurden entfernt und durch die relevanten Inhalte ersetzt (Fate-Nr. 320121).
    </para>
   </listitem>
  </itemizedlist>

  <itemizedlist mark="bullet" spacing="normal">
   <title>Fehlerbehebungen</title>
   <listitem>
    <para>
     Informationen wurden zu AppArmor während des Upgrades in <xref linkend="upgrade-consider-points"/> eingefügt (<link xlink:href="https://bugzilla.suse.com/show_bug.cgi?id=1137945"/>).
    </para>
   </listitem>
   <listitem>
    <para>
     Informationen wurden zu CDTB-Clustern, die kein Online-Upgrade unterstützen, in <xref linkend="upgrade-consider-points"/> eingefügt (<link xlink:href="https://bugzilla.suse.com/show_bug.cgi?id=1129108"/>).
    </para>
   </listitem>
   <listitem>
    <para>
     Informationen zu Ceph-Services auf denselben Computern in Hochverfügbarkeits-Einrichtungen wurden in <xref linkend="sec-as-ganesha-ha-ap"/> eingefügt (<link xlink:href="https://bugzilla.suse.com/show_bug.cgi?id=1136871"/>).
    </para>
   </listitem>
   <listitem>
    <para>
     Ein Tipp zu bezuglosen Paketen wurde in <xref linkend="upgrade-one-node"/> eingefügt (<link xlink:href="https://bugzilla.suse.com/show_bug.cgi?id=1136624"/>).
    </para>
   </listitem>
   <listitem>
    <para>
     <filename>profile-*</filename> wurde in <xref linkend="dev-env"/> mit <filename>role-storage</filename> aktualisiert (<link xlink:href="https://bugzilla.suse.com/show_bug.cgi?id=1138181"/>).
    </para>
   </listitem>
   <listitem>
    <para>
     <xref linkend="upgrade-drive-groups"/> wurde hinzugefügt (<link xlink:href="https://bugzilla.suse.com/show_bug.cgi?id=1135340"/>).
    </para>
   </listitem>
   <listitem>
    <para>
     <xref linkend="upgrade-mds"/> wurde hinzugefügt (<link xlink:href="https://bugzilla.suse.com/show_bug.cgi?id=1135064"/>).
    </para>
   </listitem>
   <listitem>
    <para>
     Ein Hinweis, dass der MDS-Cluster verkleinert werden muss, wurde in <xref linkend="upgrade-consider-points"/> eingefügt (<link xlink:href="https://bugzilla.suse.com/show_bug.cgi?id=1134826"/>).
    </para>
   </listitem>
   <listitem>
    <para>
     Die Konfigurationsdatei wurde durch <filename>/srv/pillar/ceph/stack/global.yml</filename> ersetzt (<link xlink:href="https://bugzilla.suse.com/show_bug.cgi?id=1129191"/>).
    </para>
   </listitem>
   <listitem>
    <para>
     Verschiedene Teile von <xref linkend="cha-ses-cifs"/> wurden aktualisiert (<link xlink:href="https://bugzilla.suse.com/show_bug.cgi?id=1101478"/>).
    </para>
   </listitem>
   <listitem>
    <para>
     <filename>master_minion.sls</filename> wurde aus <xref linkend="ceph-install-stack"/> gelöscht (<link xlink:href="https://bugzilla.suse.com/show_bug.cgi?id=1090921"/>).
    </para>
   </listitem>
   <listitem>
    <para>
     Das Paket <package>deepsea-cli</package> wurde in <xref linkend="deepsea-cli"/> erwähnt (<link xlink:href="https://bugzilla.suse.com/show_bug.cgi?id=1087454"/>).
    </para>
   </listitem>
  </itemizedlist>
 </sect1>
</appendix>
