<?xml version="1.0" encoding="UTF-8"?>
<!DOCTYPE appendix
[
  <!ENTITY % entities SYSTEM "entity-decl.ent">
    %entities;
]>
<appendix xmlns="http://docbook.org/ns/docbook"
 xmlns:xi="http://www.w3.org/2001/XInclude"
 xmlns:xlink="http://www.w3.org/1999/xlink" version="5.0" xml:id="ap.deploy.docupdate">
 <title>Documentation Updates</title>
 <info>
  <dm:docmanager xmlns:dm="urn:x-suse:ns:docmanager">
   <dm:maintainer>tbazant@suse.com</dm:maintainer>
   <dm:status>editing</dm:status>
   <dm:deadline></dm:deadline>
   <dm:priority></dm:priority>
   <dm:translation></dm:translation>
   <dm:languages></dm:languages>
   <dm:release>SES5</dm:release>
  </dm:docmanager>
 </info>
 <para>
  This chapter lists content changes for this document since the initial
  release of &productname; 4. You can find changes related to the cluster
  deployment that apply to previous versions in
  <link
   xlink:href="https://www.suse.com/documentation/ses-4/book_storage_admin/data/ap_adm_docupdate.html"/>.
 </para>
 <para>
  The document was updated on the following dates:
 </para>
<!--list of xrefs, latest date sorted upmost-->
 <itemizedlist mark="bullet" spacing="normal">
  <listitem>
   <para>
    <xref linkend="sec.depl.docupdates.5" xrefstyle="SectTitleOnPage"/>
   </para>
  </listitem>
 </itemizedlist>
<!--start of actual changelog-->
 <sect1 xml:id="sec.depl.docupdates.5">
  <title>May, 2017 (Release of &productname; 5)</title>

  <variablelist>
   <varlistentry>
    <term>General Updates</term>
    <listitem>
     <para/>
     <itemizedlist mark="bullet" spacing="normal">
      <listitem>
       <para>
        Added <xref linkend="ceph.upgrade.3to5"/> (Fate #323072).
       </para>
      </listitem>
      <listitem>
       <para>
        Added <xref linkend="deepsea.restart.specific"/>.
       </para>
      </listitem>
      <listitem>
       <para>
        Removed the obsolete <command>&crow;</command> installation tool in
        favor of &deepsea;.
       </para>
      </listitem>
      <listitem>
       <para>
        Removed the obsolete <command>ceph-deploy</command> tool in favor of
        &deepsea;.
       </para>
      </listitem>
      <listitem>
       <para>
        Updated <xref linkend="salt.adding.nodes"/> and added
        <xref
         linkend="salt.adding.services"/>.
       </para>
      </listitem>
      <listitem>
       <para>
        Added <xref linkend="cha.ceph.nfsganesha"/>.
       </para>
      </listitem>
      <listitem>
       <para>
        Updated <xref linkend="storage.bp.hwreq"/>
        (<link xlink:href="https://bugzilla.suse.com/show_bug.cgi?id=1029544"/> and
        <link xlink:href="https://bugzilla.suse.com/show_bug.cgi?id=1042283"/>).
       </para>
      </listitem>
      <listitem>
       <para>
        Updated <xref linkend="cha.as.ganesha"/>
        (<link xlink:href="https://bugzilla.suse.com/show_bug.cgi?id=1036495"/>,
        <link xlink:href="https://bugzilla.suse.com/show_bug.cgi?id=1031444"/>,
        FATE#322464).
       </para>
      </listitem>
      <listitem>
       <para>
        Sync Modules documented, including Elasticsearch. See <xref linkend="ceph.rgw.sync"/>
        (FATE#321614).
       </para>
      </listitem>
     </itemizedlist>
    </listitem>
   </varlistentry>
  </variablelist>

  <variablelist>
   <varlistentry>
    <term>Bugfixes</term>
    <listitem>
     <itemizedlist mark="bullet" spacing="normal">
      <listitem>
       <para>
        Added a new &deepsea; role &mgr;
        (<link xlink:href="https://bugzilla.suse.com/show_bug.cgi?id=1047472"/>).
       </para>
      </listitem>
      <listitem>
       <para>
        Added <xref linkend="ceph.upgrade.4to5cephdeloy"/>
        (<link xlink:href="https://bugzilla.suse.com/show_bug.cgi?id=1048436"/>).
       </para>
      </listitem>
      <listitem>
       <para>
        Made Stage 0 fully optional in <xref linkend="deepsea.stage.description"/>
        (<link xlink:href="https://bugzilla.suse.com/show_bug.cgi?id=1045845"/>).
       </para>
      </listitem>
      <listitem>
       <para>
        Updated the list of default pools in <xref linkend="ses.rgw.config"/>
        (<link xlink:href="https://bugzilla.suse.com/show_bug.cgi?id=1034039"/>).
       </para>
      </listitem>
      <listitem>
       <para>
        Added an 'important' snippet about &rgw; being deployed by &deepsea;
        now in <xref linkend="cha.ceph.additional.software.installation"/>
        (<link xlink:href="https://bugzilla.suse.com/show_bug.cgi?id=1044928"/>).
       </para>
      </listitem>
      <listitem>
       <para>
        Fixed shell script in <xref linkend="ceph.install.stack"/>
        (<link xlink:href="https://bugzilla.suse.com/show_bug.cgi?id=1044684"/>).
       </para>
      </listitem>
      <listitem>
       <para>
        Added <xref linkend="ceph.upgrade.luminous_flag"/>
        (<link xlink:href="https://bugzilla.suse.com/show_bug.cgi?id=1040750"/>).
       </para>
      </listitem>
      <listitem>
       <para>
        Added annotation to the example <filename>policy.cfg</filename> in
        <xref
         linkend="deepsea.example.policy_cfg"/>
        (<link xlink:href="https://bugzilla.suse.com/show_bug.cgi?id=1042691"/>).
       </para>
      </listitem>
      <listitem>
       <para>
        Improved commands for OSD disk zapping in
        <xref linkend="ceph.install.stack"/>
        (<link xlink:href="https://bugzilla.suse.com/show_bug.cgi?id=1042074"/>).
       </para>
      </listitem>
      <listitem>
       <para>
        Removed an advice to install <literal>salt-minion</literal> on
        &smaster; in <xref linkend="ceph.install.stack"/>
        (<link xlink:href="https://bugzilla.suse.com/show_bug.cgi?id=1041590"/>).
       </para>
      </listitem>
      <listitem>
       <para>
        Disable &aa; in <xref linkend="ceph.install.stack"/> and
        <xref
         linkend="ceph.upgrade.4to5"/>
        (<link xlink:href="https://bugzilla.suse.com/show_bug.cgi?id=1039852"/>).
       </para>
      </listitem>
      <listitem>
       <para>
        Added firewall recommendation to <xref linkend="ceph.install.stack"/>
        (<link xlink:href="https://bugzilla.suse.com/show_bug.cgi?id=1039344"/>).
       </para>
      </listitem>
      <listitem>
       <para>
        Removed XML-RPC references from &oa; &systemd; command lines in
        <xref
         linkend="using.customized.files"/>
        (<link xlink:href="https://bugzilla.suse.com/show_bug.cgi?id=1037371"/>).
       </para>
      </listitem>
      <listitem>
       <para>
        Fixed YAML syntax in <xref linkend="ceph.install.stack"/>
        (<link xlink:href="https://bugzilla.suse.com/show_bug.cgi?id=1035498"/>).
       </para>
      </listitem>
      <listitem>
       <para>
        Added the 'ganesha' role explanation in
        <xref linkend="policy.role.assignment"/>
        (<link xlink:href="https://bugzilla.suse.com/show_bug.cgi?id=1037365"/>).
       </para>
      </listitem>
      <listitem>
       <para>
        Clarified and improved text flow in <xref linkend="policy.configuration"/>
        (<link xlink:href="https://bugzilla.suse.com/show_bug.cgi?id=1037360"/>).
       </para>
      </listitem>
      <listitem>
       <para>
        Added <xref linkend="deepsea.rolling_updates"/>
        (<link xlink:href="https://bugzilla.suse.com/show_bug.cgi?id=1036337"/>).
       </para>
      </listitem>
      <listitem>
       <para>
        Added the &storage; 4 to 5 upgrade procedure in
        <xref linkend="ceph.upgrade.4to5"/>
        (<link xlink:href="https://bugzilla.suse.com/show_bug.cgi?id=1036266"/>).
       </para>
      </listitem>
      <listitem>
       <para>
        Replaced the term 'provisioning' with 'preparation' in
        <xref linkend="ceph.install.stack"/>
        (<link xlink:href="https://bugzilla.suse.com/show_bug.cgi?id=1036400"/>
        and
        <link xlink:href="https://bugzilla.suse.com/show_bug.cgi?id=1036492"/>).
       </para>
      </listitem>
      <listitem>
       <para>
        Added warning about advanced techniques in
        <xref linkend="deepsea.policy.filtering"/>
        (<link xlink:href="https://bugzilla.suse.com/show_bug.cgi?id=1036278"/>).
       </para>
      </listitem>
      <listitem>
       <para>
        Replaced redundant <literal>role-admin</literal> assignment in
        <xref
         linkend="deepsea.example.policy_cfg"/>
        (<link xlink:href="https://bugzilla.suse.com/show_bug.cgi?id=1036506"/>).
       </para>
      </listitem>
      <listitem>
       <para>
        Improved <xref linkend="deepsea.stage.description"/> and
        <xref
         linkend="ceph.install.stack"/>
        (<link xlink:href="https://bugzilla.suse.com/show_bug.cgi?id=1036278"/>).
       </para>
      </listitem>
      <listitem>
       <para>
        Aligned command prompts and fixed wording in
        <xref linkend="salt.node.removing"/>
        (<link xlink:href="https://bugzilla.suse.com/show_bug.cgi?id=1036329"/>).
       </para>
      </listitem>
      <listitem>
       <para>
        Added deployment steps modifications in
        <xref linkend="using.customized.files"/>
        (<link xlink:href="https://bugzilla.suse.com/show_bug.cgi?id=1026782"/>).
       </para>
      </listitem>
      <listitem>
       <para>
        Clarified and enhanced <xref linkend="ceph.install.saltstack"/> as
        suggested by
        (<link xlink:href="https://bugzilla.suse.com/show_bug.cgi?id=1020920"/>).
       </para>
      </listitem>
      <listitem>
       <para>
        Recommended enabling custom &oa; services in
        <xref linkend="using.customized.files"/>
        (<link xlink:href="https://bugzilla.suse.com/show_bug.cgi?id=989349"/>).
       </para>
      </listitem>
      <listitem>
       <para>
        Moved network recommendations to <xref linkend="storage.bp.hwreq"/> and
        included <xref linkend="storage.bp.net.private"/>
        (<link xlink:href="https://bugzilla.suse.com/show_bug.cgi?id=1026569"/>).
       </para>
      </listitem>
      <listitem>
       <para>
        Added tip on an existing <command>rbdmap</command> &systemd; service
        file in <xref linkend="storage.bp.integration.mount_rbd"/>
        (<link xlink:href="https://bugzilla.suse.com/show_bug.cgi?id=1015748"/>).
       </para>
      </listitem>
     </itemizedlist>
    </listitem>
   </varlistentry>
  </variablelist>
 </sect1>
</appendix>
