<?xml version="1.0" encoding="UTF-8"?>
<sect1 xmlns="http://docbook.org/ns/docbook" xmlns:xi="http://www.w3.org/2001/XInclude" xmlns:xlink="http://www.w3.org/1999/xlink" xml:base="common_intro_contributors.xml" version="5.0">
 <title>Colaboradores de Ceph</title>

 <info>
  <dm:docmanager xmlns:dm="urn:x-suse:ns:docmanager">
   <dm:translation>sí</dm:translation>
   <dm:release>SES 7</dm:release>
  </dm:docmanager>
 </info>

 <para>
  El proyecto Ceph y su documentación son el resultado del trabajo de cientos de colaboradores y organizaciones. Consulte <link xlink:href="https://ceph.com/contributors/"/> para obtener más información.
 </para>
</sect1>
