<?xml version="1.0" encoding="UTF-8"?>
<sect1 xmlns="http://docbook.org/ns/docbook" xmlns:xi="http://www.w3.org/2001/XInclude" xmlns:xlink="http://www.w3.org/1999/xlink" xml:base="common_intro_available_doc_i.xml" version="5.0">
 <title>Documentación disponible</title>

 <info>
      <dm:docmanager xmlns:dm="urn:x-suse:ns:docmanager">
        <dm:maintainer>tbazant@suse.com</dm:maintainer>
        <dm:status>editar</dm:status>
        <dm:deadline/>
        <dm:priority/>
        <dm:translation>sí</dm:translation>
        <dm:languages/>
        <dm:release>SES 5</dm:release>
      </dm:docmanager>
    </info>
    <para>

  Los manuales disponibles para este producto son los siguientes:
 </para>

 <variablelist>
  <varlistentry>
   <term><xref linkend="book-storage-admin"/>
   </term>
   <listitem>
    <para>
     La guía describe varias tareas de administración que normalmente se llevan a cabo después de la instalación. Esta guía también incluye los pasos necesarios para integrar Ceph con soluciones de virtualización como <systemitem class="library">libvirt</systemitem>, Xen o KVM; así como formas para acceder a objetos almacenados en el clúster mediante pasarelas iSCSI y RADOS.
    </para>
   </listitem>
  </varlistentry>
  <varlistentry>
   <term><xref linkend="book-storage-deployment"/>
   </term>
   <listitem>
    <para>
     Este manual sirve de guía para los pasos de instalación del clúster de Ceph y de todos los servicios relacionados con Ceph. También muestra una estructura de clúster de Ceph básica y proporciona la terminología relacionada.
    </para>
   </listitem>
  </varlistentry>
 </variablelist>

 <para>
  Encontrará las versiones en formato HTML de los manuales de productos en el sistema instalado, en <filename>/usr/share/doc/manual</filename>. Las últimas actualizaciones de la documentación están en <link xlink:href="http://www.suse.com/documentation"/>, donde puede descargar los manuales para el producto en varios formatos.
 </para>
</sect1>
