<?xml version="1.0" encoding="UTF-8"?>
<glossary xmlns="http://docbook.org/ns/docbook" xmlns:xi="http://www.w3.org/2001/XInclude" xmlns:xlink="http://www.w3.org/1999/xlink" xml:base="ses_glossary.xml" version="5.0">

 <title>词汇表</title>
 <info>
  <dm:docmanager xmlns:dm="urn:x-suse:ns:docmanager">
   <dm:translation>是</dm:translation>
   <dm:release>SES 7</dm:release>
  </dm:docmanager>
 </info>
 <glossdiv>
  <title>一般</title>
  <glossentry><glossterm>管理节点</glossterm>
   <glossdef>
    <para>
     在其上运行与 Ceph 相关的命令以管理集群主机的主机。
    </para>
   </glossdef>
  </glossentry>
  <glossentry><glossterm>Alertmanager</glossterm>
   <glossdef>
    <para>
     用于处理 Prometheus 服务器发送的告警并通知最终用户的单个二进制文件。
    </para>
   </glossdef>
  </glossentry>
  <glossentry><glossterm>存档同步扩展模块</glossterm>
   <glossdef>
    <para>
     允许创建对象网关区域以保留 S3 对象版本历史记录的扩展模块。
    </para>
   </glossdef>
  </glossentry>
  <glossentry><glossterm>存储桶</glossterm>
   <glossdef>
    <para>
     将其他节点聚合成物理位置层次结构的一个点。
    </para>
   </glossdef>
  </glossentry>
  <glossentry><glossterm>cephadm</glossterm>
   <glossdef>
    <para>
     cephadm 用于部署和管理 Ceph 集群，它会通过 SSH 从 Manager 守护进程连接到主机以添加、删除或更新 Ceph 守护进程容器。
    </para>
   </glossdef>
  </glossentry>
  <glossentry><glossterm>CephFS</glossterm>
   <glossdef>
    <para>
     Ceph 文件系统。
    </para>
   </glossdef>
  </glossentry>
  <glossentry><glossterm>CephX</glossterm>
   <glossdef>
    <para>
     Ceph 身份验证协议。Cephx 操作与 Kerberos 类似，但它没有单一故障点。
    </para>
   </glossdef>
  </glossentry>
  <glossentry><glossterm>Ceph 客户端</glossterm>
   <glossdef>
    <para>
     可以访问 Ceph 存储集群的 Ceph 组件集合。其中包括对象网关、Ceph 块设备、CephFS 及其相应的库、内核模块和 FUSE 客户端。
    </para>
   </glossdef>
  </glossentry>
  <glossentry><glossterm><systemitem class="resource">ceph-salt</systemitem></glossterm>
   <glossdef>
    <para>
     提供使用 Salt 部署由 cephadm 管理的 Ceph 集群的工具。
    </para>
   </glossdef>
  </glossentry>
  <glossentry><glossterm>Ceph 存储集群</glossterm>
   <glossdef>
    <para>
     用于存储用户数据的存储软件的核心集合。此类集合由 Ceph Monitor 和 OSD 组成。
    </para>
   </glossdef>
  </glossentry>
  <glossentry><glossterm>CRUSH、CRUSH 索引</glossterm>
   <glossdef>
    <para>
     <emphasis>基于可缩放哈希的受控复制</emphasis>：通过计算数据存储位置来确定如何存储和检索数据的算法。CRUSH 需要获取集群的索引来以伪随机的方式在 OSD 中存储和检索数据，并以一致的方式在整个集群中分布数据。
    </para>
   </glossdef>
  </glossentry>
  <glossentry><glossterm>CRUSH 规则</glossterm>
   <glossdef>
    <para>
     适用于某个特定存储池或多个存储池的 CRUSH 数据归置规则。
    </para>
   </glossdef>
  </glossentry>
  <glossentry><glossterm>Ceph Dashboard</glossterm>
   <glossdef>
    <para>
     一个内置的基于 Web 的 Ceph 管理和监控应用，负责管理集群的各个方面和对象。仪表盘作为 Ceph Manager 模块实施。
    </para>
   </glossdef>
  </glossentry>
  <glossentry><glossterm>DriveGroups</glossterm>
   <glossdef>
    <para>
     DriveGroups 是可映射到物理驱动器的一个或多个 OSD 布局的声明。OSD 布局定义了 Ceph 如何在符合指定准则的媒体上实际分配 OSD 存储。
    </para>
   </glossdef>
  </glossentry>
  <glossentry><glossterm>Grafana</glossterm>
   <glossdef>
    <para>
     数据库分析和监视解决方案。
    </para>
   </glossdef>
  </glossentry>
  <glossentry><glossterm>元数据服务器</glossterm>
   <glossdef>
    <para>
     元数据服务器或 MDS 是 Ceph 元数据软件。
    </para>
   </glossdef>
  </glossentry>
  <glossentry><glossterm>Ceph Monitor</glossterm>
   <glossdef>
    <para>
     Ceph Monitor 或 MON 是 Ceph Monitor 软件。
    </para>
   </glossdef>
  </glossentry>
  <glossentry><glossterm>Ceph Manager</glossterm>
   <glossdef>
    <para>
     Ceph Manager 或 MGR 是 Ceph Manager 软件，会将整个集群的所有状态收集到一处。
    </para>
   </glossdef>
  </glossentry>
  <glossentry><glossterm>节点</glossterm>
   <glossdef>
    <para>
     Ceph 集群中的任何一台计算机或服务器。
    </para>
   </glossdef>
  </glossentry>
  <glossentry><glossterm>OSD</glossterm>
   <glossdef>
    <para>
     <emphasis>对象存储设备</emphasis>：一个物理或逻辑存储单元。
    </para>
   </glossdef>
  </glossentry>
  <glossentry><glossterm>Ceph OSD 守护进程</glossterm>
   <glossdef>
    <para>
     <command>ceph-osd</command> 守护进程是 Ceph 的组件，负责在本地文件系统上存储对象并在网络中提供对它们的访问。
    </para>
   </glossdef>
  </glossentry>
  <glossentry><glossterm>OSD 节点</glossterm>
   <glossdef>
    <para>
     一个集群节点，用于存储数据、处理数据复制、恢复、回填、重新平衡以及通过检查其他 Ceph OSD 守护进程为 Ceph Monitor 提供某些监视信息。
    </para>
   </glossdef>
  </glossentry>
  <glossentry><glossterm>Ceph 对象存储</glossterm>
   <glossdef>
    <para>
     对象存储“产品”、服务或功能，由 Ceph 存储集群和 Ceph 对象网关组成。
    </para>
   </glossdef>
  </glossentry>
  <glossentry><glossterm>对象网关</glossterm>
   <glossdef>
    <para>
     Ceph 对象存储的 S3/Swift 网关组件。也称为 RADOS 网关 (RGW)。
    </para>
   </glossdef>
  </glossentry>
  <glossentry><glossterm>PG</glossterm>
   <glossdef>
    <para>
     归置组：<emphasis>存储池</emphasis>的细分，用于性能调节。
    </para>
   </glossdef>
  </glossentry>
  <glossentry><glossterm>小版本</glossterm>
   <glossdef>
    <para>
     任何只包含 bug 或安全修复的临时版本。
    </para>
   </glossdef>
  </glossentry>
  <glossentry><glossterm>池</glossterm>
   <glossdef>
    <para>
     用于存储磁盘映像等对象的逻辑分区。
    </para>
   </glossdef>
  </glossentry>
  <glossentry><glossterm>Prometheus</glossterm>
   <glossdef>
    <para>
     系统监视和警告工具箱。
    </para>
   </glossdef>
  </glossentry>
  <glossentry><glossterm>可靠自主分布式对象存储 (RADOS)</glossterm>
   <glossdef>
    <para>
     用于存储用户数据的存储软件的核心集合 (MON+OSD)。
    </para>
   </glossdef>
  </glossentry>
  <glossentry><glossterm>RADOS 块设备 (RBD)</glossterm>
   <glossdef>
    <para>
     Ceph 的块存储组件。也称为 Ceph 块设备。
    </para>
   </glossdef>
  </glossentry>
  <glossentry><glossterm>规则组</glossterm>
   <glossdef>
    <para>
     用于确定存储池的数据归置的规则。
    </para>
   </glossdef>
  </glossentry>
  <glossentry><glossterm>路由树</glossterm>
   <glossdef>
    <para>
     该术语指的是展示接收器可运行的不同路由的任何示意图。
    </para>
   </glossdef>
  </glossentry>
  <glossentry><glossterm>Samba</glossterm>
   <glossdef>
    <para>
     Windows 集成软件。
    </para>
   </glossdef>
  </glossentry>
  <glossentry><glossterm>Samba 网关</glossterm>
   <glossdef>
    <para>
     Samba 网关加入到 Windows 域中的 Active Directory，以进行用户身份验证和授权。
    </para>
   </glossdef>
  </glossentry>
  <glossentry><glossterm>多区域</glossterm>
   <glossdef>
    <para/>
   </glossdef>
  </glossentry>
  <glossentry><glossterm>区域组</glossterm>
   <glossdef>
    <para/>
   </glossdef>
  </glossentry>
 </glossdiv>
</glossary>
